{
  "version": 1,
  "updatedAt": "2026-06-13",
  "note": "Vintedge 対応モデル相場表（運営が手動更新する参考価格。出典・基準日つき）",
  "models": [
    {
      "id": "watch.rolex.daytona.126500ln",
      "category": "watch",
      "brand": "ロレックス",
      "name": "コスモグラフ デイトナ",
      "detail": "Ref.126500LN（黒文字盤）",
      "priceYen": 4800000,
      "sourceName": "銀座ブランドレックス・クォーク調べ",
      "sourceNote": "実売価格帯400万円台後半〜500万円の中間値",
      "asOf": "2026-02-05"
    },
    {
      "id": "watch.rolex.submariner-date.126610ln",
      "category": "watch",
      "brand": "ロレックス",
      "name": "サブマリーナ デイト",
      "detail": "Ref.126610LN",
      "priceYen": 2450000,
      "sourceName": "ロレックス専門店クォーク調べ",
      "sourceNote": "中古販売価格（2021年製247万円）を参考",
      "asOf": "2026-06-13"
    },
    {
      "id": "watch.rolex.gmt-master2.126710blnr",
      "category": "watch",
      "brand": "ロレックス",
      "name": "GMTマスターII（バットマン）",
      "detail": "Ref.126710BLNR",
      "priceYen": 2770000,
      "sourceName": "銀座ブランドレックス",
      "sourceNote": "2026年5月の平均買取相場",
      "asOf": "2026-06-01"
    },
    {
      "id": "watch.rolex.explorer1.124270",
      "category": "watch",
      "brand": "ロレックス",
      "name": "エクスプローラーI",
      "detail": "Ref.124270（36mm）",
      "priceYen": 1250000,
      "sourceName": "銀座ブランドレックス",
      "sourceNote": "市場価格は新品定価（120万円台）前後",
      "asOf": "2026-02-05"
    },
    {
      "id": "watch.rolex.explorer2.226570",
      "category": "watch",
      "brand": "ロレックス",
      "name": "エクスプローラーII",
      "detail": "Ref.226570",
      "priceYen": 1580000,
      "sourceName": "銀座ブランドレックス",
      "sourceNote": "新品定価1,576,300円・市場は安定した価格帯",
      "asOf": "2026-02-05"
    },
    {
      "id": "tcg.pokemon.charizard-vmax-hr-promo.psa10",
      "category": "tradingCard",
      "brand": "ポケモンカード",
      "name": "リザードンVMAX HR（争奪戦プロモ）PSA10",
      "detail": "PSA10鑑定品",
      "priceYen": 1930000,
      "sourceName": "ポケカチ（altema）",
      "sourceNote": "ショップ・フリマ調査ベースの相場",
      "asOf": "2026-06-10"
    },
    {
      "id": "tcg.pokemon.mega-charizard-x-ex-sar.psa10",
      "category": "tradingCard",
      "brand": "ポケモンカード",
      "name": "メガリザードンXex SAR PSA10",
      "detail": "PSA10鑑定品",
      "priceYen": 207000,
      "sourceName": "ポケカチ（altema）",
      "sourceNote": "ショップ・フリマ調査ベースの相場",
      "asOf": "2026-06-10"
    },
    {
      "id": "tcg.pokemon.charizard-ex-sr.psa10",
      "category": "tradingCard",
      "brand": "ポケモンカード",
      "name": "リザードンex SR PSA10",
      "detail": "PSA10鑑定品",
      "priceYen": 29300,
      "sourceName": "ポケカチ（altema）",
      "sourceNote": "ショップ・フリマ調査ベースの相場",
      "asOf": "2026-06-10"
    },
    {
      "id": "tcg.pokemon.mario-pikachu.psa10",
      "category": "tradingCard",
      "brand": "ポケモンカード",
      "name": "マリオピカチュウ（プロモ）PSA10",
      "detail": "PSA10鑑定品",
      "priceYen": 5800000,
      "sourceName": "ポケカチ（altema）",
      "sourceNote": "ショップ・フリマ調査ベースの相場",
      "asOf": "2026-06-10"
    },
    {
      "id": "tcg.pokemon.shining-mew-old.psa10",
      "category": "tradingCard",
      "brand": "ポケモンカード",
      "name": "ひかるミュウ（旧裏）PSA10",
      "detail": "PSA10鑑定品",
      "priceYen": 5800000,
      "sourceName": "ポケカチ（altema）",
      "sourceNote": "ショップ・フリマ調査ベースの相場",
      "asOf": "2026-06-10"
    },
    {
      "id": "tcg.pokemon.shining-gyarados-old.psa10",
      "category": "tradingCard",
      "brand": "ポケモンカード",
      "name": "ひかるギャラドス（旧裏）PSA10",
      "detail": "PSA10鑑定品",
      "priceYen": 6600000,
      "sourceName": "ポケカチ（altema）",
      "sourceNote": "ショップ・フリマ調査ベースの相場",
      "asOf": "2026-06-10"
    },
    {
      "id": "tcg.yugioh.blue-eyes.initial-secret",
      "category": "tradingCard",
      "brand": "遊戯王",
      "name": "青眼の白龍（初期シークレット）",
      "detail": "シクブル",
      "priceYen": 5000000,
      "sourceName": "カードラッシュ買取価格",
      "sourceNote": "販売価格は1,080万円",
      "asOf": "2026-06-13"
    },
    {
      "id": "tcg.yugioh.blue-eyes.english-ultra",
      "category": "tradingCard",
      "brand": "遊戯王",
      "name": "青眼の白龍 ウルトラ（英語版）",
      "detail": "Blue-Eyes White Dragon",
      "priceYen": 2800000,
      "sourceName": "カードラッシュ買取価格",
      "sourceNote": "販売価格は358万円",
      "asOf": "2026-06-13"
    },
    {
      "id": "tcg.yugioh.blue-eyes.kanji-ultra",
      "category": "tradingCard",
      "brand": "遊戯王",
      "name": "藍眼白龍 ウルトラ（漢字版）",
      "detail": "青眼の白龍 漢字版",
      "priceYen": 2300000,
      "sourceName": "カードラッシュ買取価格",
      "sourceNote": "販売価格は298万円",
      "asOf": "2026-06-13"
    },
    {
      "id": "wine.drc.romanee-conti.2020",
      "category": "wine",
      "brand": "DRC",
      "name": "ロマネ・コンティ 2020",
      "detail": "正規品・付属品ありが前提",
      "priceYen": 2900000,
      "sourceName": "大黒屋 買取参考価格",
      "sourceNote": "買取参考価格（今売る場合の目安）",
      "asOf": "2026-06-12"
    },
    {
      "id": "wine.drc.montrachet.2015",
      "category": "wine",
      "brand": "DRC",
      "name": "モンラッシェ 2015",
      "detail": "",
      "priceYen": 800000,
      "sourceName": "大黒屋 買取参考価格",
      "sourceNote": "買取参考価格（今売る場合の目安）",
      "asOf": "2026-06-12"
    },
    {
      "id": "wine.drc.la-tache.2019",
      "category": "wine",
      "brand": "DRC",
      "name": "ラ・ターシュ 2019",
      "detail": "",
      "priceYen": 650000,
      "sourceName": "大黒屋 買取参考価格",
      "sourceNote": "買取参考価格（今売る場合の目安）",
      "asOf": "2026-06-12"
    },
    {
      "id": "wine.drc.richebourg.2019",
      "category": "wine",
      "brand": "DRC",
      "name": "リシュブール 2019",
      "detail": "",
      "priceYen": 410000,
      "sourceName": "大黒屋 買取参考価格",
      "sourceNote": "買取参考価格（今売る場合の目安）",
      "asOf": "2026-06-12"
    },
    {
      "id": "wine.petrus.2005",
      "category": "wine",
      "brand": "シャトー・ペトリュス",
      "name": "ペトリュス 2005",
      "detail": "",
      "priceYen": 370000,
      "sourceName": "大黒屋 買取参考価格",
      "sourceNote": "買取参考価格（今売る場合の目安）",
      "asOf": "2026-06-12"
    },
    {
      "id": "wine.lafite.2007",
      "category": "wine",
      "brand": "シャトー・ラフィット・ロートシルト",
      "name": "ラフィット・ロートシルト 2007",
      "detail": "5大シャトー",
      "priceYen": 65000,
      "sourceName": "大黒屋 買取参考価格",
      "sourceNote": "買取参考価格（今売る場合の目安）",
      "asOf": "2026-06-12"
    },
    {
      "id": "wine.margaux.1992",
      "category": "wine",
      "brand": "シャトー・マルゴー",
      "name": "マルゴー 1992",
      "detail": "5大シャトー",
      "priceYen": 35000,
      "sourceName": "大黒屋 買取参考価格",
      "sourceNote": "買取参考価格（今売る場合の目安）",
      "asOf": "2026-06-12"
    },
    {
      "id": "wine.screaming-eagle.2011",
      "category": "wine",
      "brand": "スクリーミング・イーグル",
      "name": "スクリーミング・イーグル 2011",
      "detail": "カリフォルニア",
      "priceYen": 320000,
      "sourceName": "大黒屋 買取参考価格",
      "sourceNote": "買取参考価格（今売る場合の目安）",
      "asOf": "2026-06-12"
    },
    {
      "id": "wine.opus-one.2010",
      "category": "wine",
      "brand": "オーパス・ワン",
      "name": "オーパス・ワン 2010",
      "detail": "カリフォルニア",
      "priceYen": 43000,
      "sourceName": "大黒屋 買取参考価格",
      "sourceNote": "買取参考価格（今売る場合の目安）",
      "asOf": "2026-06-12"
    },
    {
      "id": "sneaker.nike.aj1-lost-and-found",
      "category": "sneaker",
      "brand": "Nike",
      "name": "Air Jordan 1 High OG Lost & Found (Chicago)",
      "detail": "DZ5485-612",
      "priceYen": 29200,
      "sourceName": "オークファン（ヤフオク落札データ）",
      "sourceNote": "直近30日の平均落札価格・状態混在",
      "sampleCount": 65,
      "asOf": "2026-06-13"
    },
    {
      "id": "sneaker.adidas.yeezy-boost-350-v2",
      "category": "sneaker",
      "brand": "adidas",
      "name": "YEEZY Boost 350 V2（全般）",
      "detail": "カラー混在の参考値",
      "priceYen": 11014,
      "sourceName": "Yahoo!オークション落札相場",
      "sourceNote": "直近30日の平均落札価格・カラー混在",
      "sampleCount": 145,
      "asOf": "2026-06-13"
    }
  ]
}
